solfege/__init__.py
solfege/note.py
solfege/scale.py
solfege-1.0.0.dist-info/LICENSE
solfege-1.0.0.dist-info/METADATA
solfege-1.0.0.dist-info/WHEEL
solfege-1.0.0.dist-info/RECORD
