Metadata-Version: 2.1
Name: solfege
Version: 1.0.0
Summary: Python library for dealing with musical scales and solfege
Home-page: https://github.com/mshafer1/py-solfege
License: MIT
Author: mshafer1
Requires-Python: >=3.9,<4.0
Classifier: License :: OSI Approved :: MIT License
Classifier: Programming Language :: Python :: 3
Classifier: Programming Language :: Python :: 3.9
Classifier: Programming Language :: Python :: 3.10
Classifier: Programming Language :: Python :: 3.11
Classifier: Programming Language :: Python :: 3.12
Project-URL: Documentation, https://mshafer1.github.io/py-solfege
